{"ticker": "FRT", "feed_timestamp": "2026-07-15 10:51:18", "spot": 122.11, "prev_close": 122.11, "options": [{"type": "C", "exp": "2026-07-17", "dte": 2, "strike": 90.0, "bid": 31.1, "ask": 33.9, "oi": 0.0, "volume": 0.0, "iv": 1.9534, "delta": 0.9989, "last_trade_time": null}, {"type": "P", "exp": "2026-07-17", "dte": 2, "strike": 90.0, "bid": 0.0, "ask": 2.15, "oi": 20.0, "volume": 0.0, "iv": 2.5617, "delta": -0.0009, "last_trade_time": "2026-05-26T13:28:28"}, {"type": "C", "exp": "2026-07-17", "dte": 2, "strike": 95.0, "bid": 26.1, "ask": 28.9, "oi": 0.0, "volume": 0.0, "iv": 1.6579, "delta": 0.9981, "last_trade_time": null}, {"type": "P", "exp": "2026-07-17", "dte": 2, "strike": 95.0, "bid": 0.0, "ask": 2.15, "oi": 0.0, "volume": 0.0, "iv": 2.2051, "delta": -0.0016, "last_trade_time": null}, {"type": "C", "exp": "2026-07-17", "dte": 2, "strike": 100.0, "bid": 21.1, "ask": 23.9, "oi": 0.0, "volume": 0.0, "iv": 1.3725, "delta": 0.9967, "last_trade_time": null}, {"type": "P", "exp": "2026-07-17", "dte": 2, "strike": 100.0, "bid": 0.0, "ask": 2.15, "oi": 20.0, "volume": 0.0, "iv": 1.8588, "delta": -0.0031, "last_trade_time": "2026-05-26T15:49:27"}, {"type": "C", "exp": "2026-07-17", "dte": 2, "strike": 105.0, "bid": 16.1, "ask": 18.9, "oi": 0.0, "volume": 0.0, "iv": 1.0943, "delta": 0.9933, "last_trade_time": null}, {"type": "P", "exp": "2026-07-17", "dte": 2, "strike": 105.0, "bid": 0.0, "ask": 2.15, "oi": 1.0, "volume": 0.0, "iv": 1.5188, "delta": -0.0065, "last_trade_time": "2026-05-14T12:39:22"}, {"type": "C", "exp": "2026-07-17", "dte": 2, "strike": 110.0, "bid": 11.1, "ask": 13.7, "oi": 0.0, "volume": 0.0, "iv": 0.7488, "delta": 0.9843, "last_trade_time": "2026-06-30T14:48:40"}, {"type": "P", "exp": "2026-07-17", "dte": 2, "strike": 110.0, "bid": 0.0, "ask": 2.15, "oi": 26.0, "volume": 0.0, "iv": 1.1798, "delta": -0.0154, "last_trade_time": "2026-06-24T10:40:32"}, {"type": "C", "exp": "2026-07-17", "dte": 2, "strike": 115.0, "bid": 5.4, "ask": 8.7, "oi": 0.0, "volume": 0.0, "iv": 0.0, "delta": 0.9538, "last_trade_time": "2026-06-30T09:45:36"}, {"type": "P", "exp": "2026-07-17", "dte": 2, "strike": 115.0, "bid": 0.0, "ask": 0.6, "oi": 279.0, "volume": 5.0, "iv": 0.5387, "delta": -0.046, "last_trade_time": "2026-07-14T10:07:15"}, {"type": "C", "exp": "2026-07-17", "dte": 2, "strike": 120.0, "bid": 1.5, "ask": 4.1, "oi": 838.0, "volume": 0.0, "iv": 0.3283, "delta": 0.7882, "last_trade_time": "2026-07-10T15:50:47"}, {"type": "P", "exp": "2026-07-17", "dte": 2, "strike": 120.0, "bid": 0.0, "ask": 2.6, "oi": 21.0, "volume": 0.0, "iv": 0.5069, "delta": -0.2122, "last_trade_time": "2026-07-02T15:38:07"}, {"type": "C", "exp": "2026-07-17", "dte": 2, "strike": 125.0, "bid": 0.0, "ask": 0.3, "oi": 935.0, "volume": 14.0, "iv": 0.2162, "delta": 0.1074, "last_trade_time": "2026-07-14T15:54:38"}, {"type": "P", "exp": "2026-07-17", "dte": 2, "strike": 125.0, "bid": 1.4, "ask": 4.1, "oi": 0.0, "volume": 0.0, "iv": 0.0, "delta": -0.8998, "last_trade_time": "2026-07-13T13:35:23"}, {"type": "C", "exp": "2026-07-17", "dte": 2, "strike": 130.0, "bid": 0.0, "ask": 1.15, "oi": 35.0, "volume": 0.0, "iv": 0.6531, "delta": 0.0114, "last_trade_time": "2026-07-07T15:48:45"}, {"type": "P", "exp": "2026-07-17", "dte": 2, "strike": 130.0, "bid": 6.2, "ask": 8.9, "oi": 0.0, "volume": 0.0, "iv": 0.0, "delta": -0.994, "last_trade_time": "2026-06-16T10:00:41"}, {"type": "C", "exp": "2026-07-17", "dte": 2, "strike": 135.0, "bid": 0.0, "ask": 0.75, "oi": 0.0, "volume": 0.0, "iv": 0.4906, "delta": 0.0028, "last_trade_time": null}, {"type": "P", "exp": "2026-07-17", "dte": 2, "strike": 135.0, "bid": 11.5, "ask": 13.9, "oi": 0.0, "volume": 0.0, "iv": 0.0, "delta": -0.9995, "last_trade_time": "2026-06-18T10:25:35"}, {"type": "C", "exp": "2026-07-17", "dte": 2, "strike": 140.0, "bid": 0.0, "ask": 2.15, "oi": 2.0, "volume": 0.0, "iv": 1.3469, "delta": 0.001, "last_trade_time": "2026-06-22T11:17:46"}, {"type": "P", "exp": "2026-07-17", "dte": 2, "strike": 140.0, "bid": 16.2, "ask": 18.9, "oi": 0.0, "volume": 0.0, "iv": 0.0, "delta": -0.9999, "last_trade_time": null}, {"type": "C", "exp": "2026-07-17", "dte": 2, "strike": 145.0, "bid": 0.0, "ask": 2.15, "oi": 0.0, "volume": 0.0, "iv": 1.5734, "delta": 0.0004, "last_trade_time": null}, {"type": "P", "exp": "2026-07-17", "dte": 2, "strike": 145.0, "bid": 21.2, "ask": 23.9, "oi": 0.0, "volume": 0.0, "iv": 0.0, "delta": -1.0, "last_trade_time": null}, {"type": "C", "exp": "2026-07-17", "dte": 2, "strike": 150.0, "bid": 0.0, "ask": 2.15, "oi": 0.0, "volume": 0.0, "iv": 1.7836, "delta": 0.0002, "last_trade_time": null}, {"type": "P", "exp": "2026-07-17", "dte": 2, "strike": 150.0, "bid": 26.2, "ask": 28.9, "oi": 0.0, "volume": 0.0, "iv": 0.0, "delta": -1.0, "last_trade_time": null}, {"type": "C", "exp": "2026-07-17", "dte": 2, "strike": 155.0, "bid": 0.0, "ask": 2.15, "oi": 0.0, "volume": 0.0, "iv": 1.9802, "delta": 0.0001, "last_trade_time": null}, {"type": "P", "exp": "2026-07-17", "dte": 2, "strike": 155.0, "bid": 31.2, "ask": 33.9, "oi": 0.0, "volume": 0.0, "iv": 0.0, "delta": -1.0, "last_trade_time": null}, {"type": "C", "exp": "2026-07-17", "dte": 2, "strike": 160.0, "bid": 0.0, "ask": 2.15, "oi": 0.0, "volume": 0.0, "iv": 2.1654, "delta": 0.0001, "last_trade_time": null}, {"type": "P", "exp": "2026-07-17", "dte": 2, "strike": 160.0, "bid": 36.2, "ask": 38.9, "oi": 0.0, "volume": 0.0, "iv": 0.0, "delta": -1.0, "last_trade_time": null}, {"type": "C", "exp": "2026-07-17", "dte": 2, "strike": 165.0, "bid": 0.0, "ask": 2.15, "oi": 8.0, "volume": 0.0, "iv": 2.3408, "delta": 0.0, "last_trade_time": "2026-07-09T10:55:52"}, {"type": "P", "exp": "2026-07-17", "dte": 2, "strike": 165.0, "bid": 41.2, "ask": 43.9, "oi": 0.0, "volume": 0.0, "iv": 0.0, "delta": -1.0, "last_trade_time": null}, {"type": "C", "exp": "2026-07-17", "dte": 2, "strike": 170.0, "bid": 0.0, "ask": 2.15, "oi": 5.0, "volume": 0.0, "iv": 2.5074, "delta": 0.0, "last_trade_time": "2026-07-09T10:32:07"}, {"type": "P", "exp": "2026-07-17", "dte": 2, "strike": 170.0, "bid": 46.2, "ask": 48.9, "oi": 0.0, "volume": 0.0, "iv": 0.0, "delta": -1.0, "last_trade_time": null}, {"type": "C", "exp": "2026-08-21", "dte": 37, "strike": 90.0, "bid": 30.8, "ask": 34.8, "oi": 0.0, "volume": 0.0, "iv": 0.6066, "delta": 0.9517, "last_trade_time": "2026-03-02T10:26:28"}, {"type": "P", "exp": "2026-08-21", "dte": 37, "strike": 90.0, "bid": 0.0, "ask": 0.6, "oi": 44.0, "volume": 0.0, "iv": 0.5471, "delta": -0.0461, "last_trade_time": "2026-05-21T13:04:54"}, {"type": "C", "exp": "2026-08-21", "dte": 37, "strike": 95.0, "bid": 25.9, "ask": 29.9, "oi": 0.0, "volume": 0.0, "iv": 0.5353, "delta": 0.9381, "last_trade_time": "2026-05-08T13:08:04"}, {"type": "P", "exp": "2026-08-21", "dte": 37, "strike": 95.0, "bid": 0.0, "ask": 2.3, "oi": 5.0, "volume": 0.0, "iv": 0.6374, "delta": -0.0597, "last_trade_time": "2026-07-08T14:58:37"}, {"type": "C", "exp": "2026-08-21", "dte": 37, "strike": 100.0, "bid": 21.0, "ask": 25.1, "oi": 0.0, "volume": 0.0, "iv": 0.4705, "delta": 0.9188, "last_trade_time": "2026-05-07T10:29:53"}, {"type": "P", "exp": "2026-08-21", "dte": 37, "strike": 100.0, "bid": 0.0, "ask": 2.3, "oi": 29.0, "volume": 0.0, "iv": 0.5386, "delta": -0.0791, "last_trade_time": "2026-06-01T12:40:02"}, {"type": "C", "exp": "2026-08-21", "dte": 37, "strike": 105.0, "bid": 16.4, "ask": 20.2, "oi": 8.0, "volume": 0.0, "iv": 0.4138, "delta": 0.89, "last_trade_time": "2026-06-10T12:43:23"}, {"type": "P", "exp": "2026-08-21", "dte": 37, "strike": 105.0, "bid": 0.05, "ask": 2.4, "oi": 801.0, "volume": 0.0, "iv": 0.4507, "delta": -0.108, "last_trade_time": "2026-05-28T13:33:44"}, {"type": "C", "exp": "2026-08-21", "dte": 37, "strike": 110.0, "bid": 11.7, "ask": 15.4, "oi": 65.0, "volume": 0.0, "iv": 0.346, "delta": 0.8446, "last_trade_time": "2026-07-10T09:41:24"}, {"type": "P", "exp": "2026-08-21", "dte": 37, "strike": 110.0, "bid": 0.0, "ask": 2.0, "oi": 2.0, "volume": 0.0, "iv": 0.3285, "delta": -0.1537, "last_trade_time": "2026-05-27T11:58:00"}, {"type": "C", "exp": "2026-08-21", "dte": 37, "strike": 115.0, "bid": 6.8, "ask": 10.8, "oi": 1022.0, "volume": 0.0, "iv": 0.2669, "delta": 0.7667, "last_trade_time": "2026-07-09T15:51:59"}, {"type": "P", "exp": "2026-08-21", "dte": 37, "strike": 115.0, "bid": 0.1, "ask": 2.2, "oi": 4.0, "volume": 0.0, "iv": 0.2459, "delta": -0.2322, "last_trade_time": "2026-06-24T11:19:12"}, {"type": "C", "exp": "2026-08-21", "dte": 37, "strike": 120.0, "bid": 3.7, "ask": 6.5, "oi": 96.0, "volume": 0.0, "iv": 0.2416, "delta": 0.6213, "last_trade_time": "2026-06-30T15:32:53"}, {"type": "P", "exp": "2026-08-21", "dte": 37, "strike": 120.0, "bid": 0.7, "ask": 3.9, "oi": 6.0, "volume": 0.0, "iv": 0.2166, "delta": -0.3795, "last_trade_time": "2026-07-13T14:58:59"}, {"type": "C", "exp": "2026-08-21", "dte": 37, "strike": 125.0, "bid": 1.65, "ask": 4.0, "oi": 68.0, "volume": 13.0, "iv": 0.2008, "delta": 0.3854, "last_trade_time": "2026-07-14T15:02:43"}, {"type": "P", "exp": "2026-08-21", "dte": 37, "strike": 125.0, "bid": 3.1, "ask": 5.9, "oi": 3.0, "volume": 0.0, "iv": 0.1905, "delta": -0.6201, "last_trade_time": "2026-06-17T15:32:14"}, {"type": "C", "exp": "2026-08-21", "dte": 37, "strike": 130.0, "bid": 0.05, "ask": 2.5, "oi": 49.0, "volume": 1.0, "iv": 0.244, "delta": 0.2041, "last_trade_time": "2026-07-14T09:37:00"}, {"type": "P", "exp": "2026-08-21", "dte": 37, "strike": 130.0, "bid": 6.2, "ask": 10.3, "oi": 0.0, "volume": 0.0, "iv": 0.186, "delta": -0.8062, "last_trade_time": null}, {"type": "C", "exp": "2026-08-21", "dte": 37, "strike": 135.0, "bid": 0.0, "ask": 2.1, "oi": 12.0, "volume": 0.0, "iv": 0.3034, "delta": 0.1207, "last_trade_time": "2026-06-24T14:53:50"}, {"type": "P", "exp": "2026-08-21", "dte": 37, "strike": 135.0, "bid": 10.8, "ask": 14.9, "oi": 0.0, "volume": 0.0, "iv": 0.1738, "delta": -0.8918, "last_trade_time": null}, {"type": "C", "exp": "2026-08-21", "dte": 37, "strike": 140.0, "bid": 0.0, "ask": 2.35, "oi": 0.0, "volume": 0.0, "iv": 0.3868, "delta": 0.08, "last_trade_time": null}, {"type": "P", "exp": "2026-08-21", "dte": 37, "strike": 140.0, "bid": 15.7, "ask": 19.7, "oi": 0.0, "volume": 0.0, "iv": 0.0, "delta": -0.9335, "last_trade_time": null}, {"type": "C", "exp": "2026-08-21", "dte": 37, "strike": 145.0, "bid": 0.0, "ask": 2.25, "oi": 0.0, "volume": 0.0, "iv": 0.446, "delta": 0.0573, "last_trade_time": null}, {"type": "P", "exp": "2026-08-21", "dte": 37, "strike": 145.0, "bid": 20.7, "ask": 24.7, "oi": 0.0, "volume": 0.0, "iv": 0.0, "delta": -0.9569, "last_trade_time": null}, {"type": "C", "exp": "2026-08-21", "dte": 37, "strike": 150.0, "bid": 0.0, "ask": 2.2, "oi": 0.0, "volume": 0.0, "iv": 0.5027, "delta": 0.0432, "last_trade_time": null}, {"type": "P", "exp": "2026-08-21", "dte": 37, "strike": 150.0, "bid": 25.7, "ask": 29.7, "oi": 0.0, "volume": 0.0, "iv": 0.0, "delta": -0.9718, "last_trade_time": null}]}